jupyter_neuroglancer/__init__.py
jupyter_neuroglancer-0.2.dist-info/LICENSE
jupyter_neuroglancer-0.2.dist-info/METADATA
jupyter_neuroglancer-0.2.dist-info/WHEEL
jupyter_neuroglancer-0.2.dist-info/top_level.txt
jupyter_neuroglancer-0.2.dist-info/RECORD
