Metadata-Version: 2.1
Name: jupyter-neuroglancer
Version: 0.2
Summary: Tiny Jupyter Wrapper for neuroglancer viewer
Author-email: Yuvi <yuvipanda@gmail.com>
License: BSD 3-Clause License
Project-URL: Repository, https://github.com/yuvipanda/jupyter-neuroglancer
License-File: LICENSE
Requires-Dist: neuroglancer
Requires-Dist: sidecar
